k0dasm/__init__.py
k0dasm/command.py
k0dasm/disassemble.py
k0dasm/listing.py
k0dasm/memory.py
k0dasm/symbols.py
k0dasm/trace.py
k0dasm/utils.py
k0dasm/tests/__init__.py
k0dasm/tests/test_disassemble.py
k0dasm-1.0.1.dist-info/LICENSE.txt
k0dasm-1.0.1.dist-info/METADATA
k0dasm-1.0.1.dist-info/WHEEL
k0dasm-1.0.1.dist-info/entry_points.txt
k0dasm-1.0.1.dist-info/top_level.txt
k0dasm-1.0.1.dist-info/RECORD
