Metadata-Version: 2.1
Name: k0dasm
Version: 1.0.1
Summary: Renesas (NEC) 78K0 disassembler
Home-page: https://github.com/mnaberez/k0dasm
Author: Mike Naberezny
Author-email: mike@naberezny.com
Maintainer: Mike Naberezny
Maintainer-email: mike@naberezny.com
License: License :: OSI Approved :: BSD License
Platform: UNKNOWN
Classifier: Development Status :: 3 - Alpha
Classifier: Environment :: Console
Classifier: Intended Audience :: Developers
Classifier: Natural Language :: English
Classifier: Operating System :: POSIX
Classifier: Programming Language :: Python
Classifier: Programming Language :: Python :: 3
Classifier: Programming Language :: Python :: 3.4
Classifier: Programming Language :: Python :: 3.5
Classifier: Programming Language :: Python :: 3.6
Classifier: Programming Language :: Python :: 3.7
Classifier: Programming Language :: Python :: 3.8
Classifier: Programming Language :: Assembly
Classifier: Topic :: Software Development :: Disassemblers
Classifier: Topic :: Software Development :: Embedded Systems
Classifier: Topic :: System :: Hardware
